README.md
setup.cfg
setup.py
ahvl/__init__.py
ahvl/hashivault.py
ahvl/helper.py
ahvl/lookup.py
ahvl/process.py
ahvl.egg-info/PKG-INFO
ahvl.egg-info/SOURCES.txt
ahvl.egg-info/dependency_links.txt
ahvl.egg-info/requires.txt
ahvl.egg-info/top_level.txt
ahvl/generate/__init__.py
ahvl/generate/gpgkey.py
ahvl/generate/password.py
ahvl/generate/salt.py
ahvl/generate/sshhostkey.py
ahvl/generate/sshkey.py
ahvl/options/__init__.py
ahvl/options/base.py
ahvl/options/hashivault.py
ahvl/options/generate/__init__.py
ahvl/options/generate/gpgkey.py
ahvl/options/generate/password.py
ahvl/options/generate/salt.py
ahvl/options/generate/sshhostkey.py
ahvl/options/generate/sshkey.py
ahvl/options/lookup/__init__.py
ahvl/options/lookup/credential.py
ahvl/options/lookup/gpgkey.py
ahvl/options/lookup/password.py
ahvl/options/lookup/sshhostkey.py
ahvl/options/lookup/sshkey.py
ahvl/options/set/__init__.py
ahvl/options/set/password.py