Metadata-Version: 2.1
Name: ahvl
Version: 1.2.1
Summary: Base libraries for the Ansible HashiCorp Vault Lookup (AHVL) Plugin by Netson
Home-page: https://github.com/netson/ahvl
Author: RH Sonnenberg
Author-email: r.sonnenberg@netson.nl
License: MIT
Download-URL: https://github.com/netson/ahvl/archive/v1.2.1.tar.gz
Keywords: ansible hashicorp vault lookup
Platform: UNKNOWN
Classifier: Programming Language :: Python :: 3
Classifier: License :: OSI Approved :: MIT License
Classifier: Operating System :: POSIX :: Linux
